LICENSE
MANIFEST.in
requirements.txt
setup.cfg
setup.py
leveldir/__init__.py
leveldir/base.py
leveldir/hex.py
leveldir/numeric.py
leveldir.egg-info/PKG-INFO
leveldir.egg-info/SOURCES.txt
leveldir.egg-info/dependency_links.txt
leveldir.egg-info/requires.txt
leveldir.egg-info/top_level.txt
tests/test_hexdir.py
tests/test_numdir.py