Metadata-Version: 2.1
Name: leveldir
Version: 0.3.2
Summary: Create multi-level directory structures
Home-page: https://holbrook.no/src/leveldir/log.html
Author: Louis Holbrook
Author-email: dev@holbrook.no
License: WTFPL
Keywords: filesystem,hex,directory
Classifier: Programming Language :: Python :: 3
Classifier: Operating System :: OS Independent
Classifier: Development Status :: 4 - Beta
Classifier: Topic :: Software Development :: Libraries
Classifier: Environment :: Console
Classifier: Intended Audience :: Developers
Classifier: License :: OSI Approved :: GNU General Public License v3 or later (GPLv3+)
Classifier: Topic :: Internet
Requires-Python: >=3.6
License-File: LICENSE
